odoo/addons/l10n_nl_account_credit_control/README.rst
odoo/addons/l10n_nl_account_credit_control/__init__.py
odoo/addons/l10n_nl_account_credit_control/__manifest__.py
odoo/addons/l10n_nl_account_credit_control/data/credit_control_policy_fee_data.xml
odoo/addons/l10n_nl_account_credit_control/i18n/l10n_nl_account_credit_control.pot
odoo/addons/l10n_nl_account_credit_control/models/__init__.py
odoo/addons/l10n_nl_account_credit_control/models/credit_control_policy.py
odoo/addons/l10n_nl_account_credit_control/models/credit_control_policy_fee.py
odoo/addons/l10n_nl_account_credit_control/readme/CONFIGURE.rst
odoo/addons/l10n_nl_account_credit_control/readme/CONTRIBUTORS.rst
odoo/addons/l10n_nl_account_credit_control/readme/DESCRIPTION.rst
odoo/addons/l10n_nl_account_credit_control/reports/report_credit_control_summary.xml
odoo/addons/l10n_nl_account_credit_control/security/ir.model.access.csv
odoo/addons/l10n_nl_account_credit_control/static/description/icon.png
odoo/addons/l10n_nl_account_credit_control/static/description/index.html
odoo/addons/l10n_nl_account_credit_control/tests/__init__.py
odoo/addons/l10n_nl_account_credit_control/tests/test_credit_control.py
odoo/addons/l10n_nl_account_credit_control/views/credit_control_policy_view.xml
odoo/addons/l10n_nl_account_credit_control/wizards/__init__.py
odoo/addons/l10n_nl_account_credit_control/wizards/credit_control_communication.py
odoo11_addon_l10n_nl_account_credit_control-11.0.1.0.0.99.dev5.dist-info/METADATA
odoo11_addon_l10n_nl_account_credit_control-11.0.1.0.0.99.dev5.dist-info/WHEEL
odoo11_addon_l10n_nl_account_credit_control-11.0.1.0.0.99.dev5.dist-info/top_level.txt
odoo11_addon_l10n_nl_account_credit_control-11.0.1.0.0.99.dev5.dist-info/RECORD
